tableau_toolkit/__init__.py
tableau_toolkit/add_commands.py
tableau_toolkit/cli.py
tableau_toolkit/cli_utils.py
tableau_toolkit/create_commands.py
tableau_toolkit/delete_commands.py
tableau_toolkit/download_commands.py
tableau_toolkit/exception_handler.py
tableau_toolkit/get_commands.py
tableau_toolkit/logging_config.py
tableau_toolkit/queries/__init__.py
tableau_toolkit/queries/customized_view_queries.py
tableau_toolkit/queries/data_alert_queries.py
tableau_toolkit/queries/datasource_queries.py
tableau_toolkit/queries/extract_refresh_queries.py
tableau_toolkit/queries/group_queries.py
tableau_toolkit/queries/site_role_queries.py
tableau_toolkit/queries/subscription_queries.py
tableau_toolkit/queries/user_queries.py
tableau_toolkit/queries/view_queries.py
tableau_toolkit/queries/workbook_queries.py
tableau_toolkit/update_commands.py
tableau_toolkit-0.1.27.dist-info/LICENSE
tableau_toolkit-0.1.27.dist-info/METADATA
tableau_toolkit-0.1.27.dist-info/WHEEL
tableau_toolkit-0.1.27.dist-info/entry_points.txt
tableau_toolkit-0.1.27.dist-info/RECORD
