Metadata-Version: 2.3
Name: tableau-toolkit
Version: 0.1.27
Summary: 
Author: Albert Wong
Author-email: albert.wong@salesforce.com
Requires-Python: ==3.13
Classifier: Programming Language :: Python :: 3
Classifier: Programming Language :: Python :: 3.13
Requires-Dist: chardet (>=5.2.0,<6.0.0)
Requires-Dist: click (>=8.1.7,<9.0.0)
Requires-Dist: psycopg2-binary (>=2.9.10,<3.0.0)
Requires-Dist: pyyaml (>=6.0.2,<7.0.0)
Requires-Dist: requests (>=2.32.3,<3.0.0)
Requires-Dist: structlog (>=25.1.0,<26.0.0)
Requires-Dist: tableauhyperapi (>=0.0.21408,<0.0.21409)
Requires-Dist: tableauserverclient (>=0.34,<0.35)
